dataframeviewer/__init__.py
dataframeviewer/__main__.py
dataframeviewer/__version__.py
dataframeviewer/axisrangedialog.py
dataframeviewer/customchartdialog.py
dataframeviewer/dataframemodel.py
dataframeviewer/dataviewer.py
dataframeviewer/dataviewerutils.py
dataframeviewer/mergedialog.py
dataframeviewer/plotviewer.py
dataframeviewer/searchdialog.py
dataframeviewer/tableviewer.py
dataframeviewer/viewerwindow.py
dataframeviewer/data/example.csv
dataframeviewer/data/stocks/FB.csv
dataframeviewer/data/stocks/GOOG.csv
dataframeviewer/docs/user_manual.pdf
dataframeviewer/settings/examples/stock_settings.json
dataframeviewer/ui/__init__.py
dataframeviewer/ui/ui_axisrangedialog.py
dataframeviewer/ui/ui_customchartdialog.py
dataframeviewer/ui/ui_dataviewer.py
dataframeviewer/ui/ui_mergedialog.py
dataframeviewer/ui/ui_plotviewer.py
dataframeviewer/ui/ui_progresswidget.py
dataframeviewer/ui/ui_searchdialog.py
dataframeviewer/ui/ui_tableeditor.py
dataframeviewer/ui/ui_tableviewer.py
dataframeviewer/ui/images/__init__.py
dataframeviewer/ui/images/app_icon.png
dataframeviewer/ui/images/resources_rc.py
tests/__init__.py
tests/test_dataframemodel.py
tests/test_dataviewer.py
tests/test_dataviewerutils.py
tests/test_tableviewer.py
dataframeviewer-1.7.3.dist-info/LICENSE
dataframeviewer-1.7.3.dist-info/METADATA
dataframeviewer-1.7.3.dist-info/WHEEL
dataframeviewer-1.7.3.dist-info/entry_points.txt
dataframeviewer-1.7.3.dist-info/top_level.txt
dataframeviewer-1.7.3.dist-info/RECORD
