Metadata-Version: 2.1
Name: dataframeviewer
Version: 1.7.3
Summary: PyQt5 application to visualize pandas DataFrames
Home-page: UNKNOWN
Author: Rafael Arvelo
Author-email: rafaelarvelo1@gmail.com
License: UNKNOWN
Platform: UNKNOWN
Classifier: Programming Language :: Python :: 3
Classifier: Operating System :: MacOS :: MacOS X
Classifier: Operating System :: Microsoft :: Windows
Requires-Python: >=3.6
Requires-Dist: pandas
Requires-Dist: numpy
Requires-Dist: PyQt5
Requires-Dist: openpyxl
Requires-Dist: matplotlib
Requires-Dist: qdarkstyle
Requires-Dist: setuptools
